keystoneauth1/__init__.py
keystoneauth1/_fair_semaphore.py
keystoneauth1/_utils.py
keystoneauth1/adapter.py
keystoneauth1/discover.py
keystoneauth1/http_basic.py
keystoneauth1/noauth.py
keystoneauth1/plugin.py
keystoneauth1/py.typed
keystoneauth1/service_token.py
keystoneauth1/session.py
keystoneauth1/token_endpoint.py
keystoneauth1/access/__init__.py
keystoneauth1/access/access.py
keystoneauth1/access/service_catalog.py
keystoneauth1/access/service_providers.py
keystoneauth1/access/types.py
keystoneauth1/exceptions/__init__.py
keystoneauth1/exceptions/auth.py
keystoneauth1/exceptions/auth_plugins.py
keystoneauth1/exceptions/base.py
keystoneauth1/exceptions/catalog.py
keystoneauth1/exceptions/connection.py
keystoneauth1/exceptions/discovery.py
keystoneauth1/exceptions/http.py
keystoneauth1/exceptions/oidc.py
keystoneauth1/exceptions/response.py
keystoneauth1/exceptions/service_providers.py
keystoneauth1/extras/__init__.py
keystoneauth1/extras/_saml2/__init__.py
keystoneauth1/extras/_saml2/_loading.py
keystoneauth1/extras/_saml2/v3/__init__.py
keystoneauth1/extras/_saml2/v3/adfs.py
keystoneauth1/extras/_saml2/v3/base.py
keystoneauth1/extras/_saml2/v3/saml2.py
keystoneauth1/extras/kerberos/__init__.py
keystoneauth1/extras/kerberos/_loading.py
keystoneauth1/extras/oauth1/__init__.py
keystoneauth1/extras/oauth1/_loading.py
keystoneauth1/extras/oauth1/v3.py
keystoneauth1/fixture/__init__.py
keystoneauth1/fixture/discovery.py
keystoneauth1/fixture/exception.py
keystoneauth1/fixture/hooks.py
keystoneauth1/fixture/keystoneauth_betamax.py
keystoneauth1/fixture/plugin.py
keystoneauth1/fixture/serializer.py
keystoneauth1/fixture/v2.py
keystoneauth1/fixture/v3.py
keystoneauth1/hacking/__init__.py
keystoneauth1/hacking/checks.py
keystoneauth1/identity/__init__.py
keystoneauth1/identity/access.py
keystoneauth1/identity/base.py
keystoneauth1/identity/v2.py
keystoneauth1/identity/generic/__init__.py
keystoneauth1/identity/generic/base.py
keystoneauth1/identity/generic/password.py
keystoneauth1-5.13.0.dist-info/licenses/AUTHORS
keystoneauth1-5.13.0.dist-info/licenses/LICENSE
keystoneauth1-5.13.0.dist-info/METADATA
keystoneauth1-5.13.0.dist-info/WHEEL
keystoneauth1-5.13.0.dist-info/entry_points.txt
keystoneauth1-5.13.0.dist-info/pbr.json
keystoneauth1-5.13.0.dist-info/top_level.txt
keystoneauth1-5.13.0.dist-info/RECORD
