Metadata-Version: 2.4
Name: keystoneauth1
Version: 5.13.0
Summary: Authentication Library for OpenStack Identity
Author-email: OpenStack <openstack-discuss@lists.openstack.org>
License: Apache-2.0
Project-URL: Documentation, https://docs.openstack.org/keystoneauth/latest/
Project-URL: Source, https://opendev.org/openstack/keystoneauth/
Project-URL: Bugs, https://bugs.launchpad.net/keystoneauth/
Project-URL: Release Notes, https://docs.openstack.org/releasenotes/keystoneauth/
Classifier: Environment :: OpenStack
Classifier: Intended Audience :: Information Technology
Classifier: Intended Audience :: System Administrators
Classifier: License :: OSI Approved :: Apache Software License
Classifier: Operating System :: POSIX :: Linux
Classifier: Programming Language :: Python
Classifier: Programming Language :: Python :: 3
Classifier: Programming Language :: Python :: 3.10
Classifier: Programming Language :: Python :: 3.11
Classifier: Programming Language :: Python :: 3.12
Classifier: Programming Language :: Python :: 3.13
Classifier: Programming Language :: Python :: Implementation :: CPython
Classifier: Programming Language :: Python :: 3 :: Only
Requires-Python: >=3.10
License-File: LICENSE
License-File: AUTHORS
Requires-Dist: pbr>=2.0.0
Requires-Dist: iso8601>=2.0.0
Requires-Dist: requests>=2.14.2
Requires-Dist: stevedore>=1.20.0
Requires-Dist: os-service-types>=1.2.0
Requires-Dist: typing-extensions>=4.12
Provides-Extra: kerberos
Requires-Dist: requests-kerberos>=0.8.0; extra == "kerberos"
Provides-Extra: saml2
Requires-Dist: lxml>=4.2.0; extra == "saml2"
Provides-Extra: oauth1
Requires-Dist: oauthlib>=0.6.2; extra == "oauth1"
Provides-Extra: betamax
Requires-Dist: betamax>=0.7.0; extra == "betamax"
Requires-Dist: fixtures>=3.0.0; extra == "betamax"
Requires-Dist: PyYAML>=3.13; extra == "betamax"
Dynamic: license-file
Dynamic: requires-dist
